cffi_stubgen/__init__.py
cffi_stubgen/__main__.py
cffi_stubgen/functions.py
cffi_stubgen/py.typed
cffi_stubgen/stubgen.py
cffi_stubgen-1.0.2.dist-info/METADATA
cffi_stubgen-1.0.2.dist-info/WHEEL
cffi_stubgen-1.0.2.dist-info/entry_points.txt
cffi_stubgen-1.0.2.dist-info/licenses/LICENSE
cffi_stubgen-1.0.2.dist-info/RECORD
