Metadata-Version: 2.4
Name: cffi-stubgen
Version: 1.0.2
Summary: PEP 561 type stubs generator for cffi modules
Project-URL: Repository, https://github.com/LorenzoPeri17/cffi-stubgen
Project-URL: Issues, https://github.com/LorenzoPeri17/cffi-stubgen/issues
Author: Lorenzo Peri
License-Expression: MIT
License-File: LICENSE
Classifier: Development Status :: 4 - Beta
Classifier: Intended Audience :: Developers
Classifier: License :: OSI Approved :: MIT License
Classifier: Operating System :: OS Independent
Classifier: Programming Language :: Python :: 3
Classifier: Programming Language :: Python :: 3.10
Classifier: Programming Language :: Python :: 3.11
Classifier: Programming Language :: Python :: 3.12
Classifier: Programming Language :: Python :: 3.13
Requires-Python: >=3.10
Requires-Dist: cffi>=1.10
Requires-Dist: pycparser>=2
Requires-Dist: types-cffi>=1.10
Requires-Dist: typing-extensions
Provides-Extra: test
Requires-Dist: pytest; extra == 'test'
